README.rst
setup.cfg
setup.py
openweathermapy/__init__.py
openweathermapy/core.py
openweathermapy/utils.py
openweathermapy.egg-info/PKG-INFO
openweathermapy.egg-info/SOURCES.txt
openweathermapy.egg-info/dependency_links.txt
openweathermapy.egg-info/top_level.txt