Metadata-Version: 1.0
Name: openweathermapy
Version: 0.6.5
Summary: Python package wrapping OpenWeatherMap.org's API 2.5
Home-page: https://github.com/crazycapivara/openweathermapy
Author: Stefan Kuethe
Author-email: crazycapivara@gmail.com
License: GPLv3
Download-URL: https://github.com/crazycapivara/openweathermapy/archive/master.zip
Keywords: openweathermap,weather data,forecast data,free weather,open weather,API 2.5
Platform: UNKNOWN
Classifier: Development Status :: 3 - Alpha
Classifier: Intended Audience :: Developers
Classifier: License :: OSI Approved :: GNU General Public License v3 (GPLv3)
Classifier: Programming Language :: Python
Classifier: Programming Language :: Python :: 2.7
Classifier: Programming Language :: Python :: 3.2
Classifier: Programming Language :: Python :: 3.3
Classifier: Programming Language :: Python :: 3.4
Classifier: Topic :: Utilities
